aos/__init__.py
aos/aos.py
aos/blueprint.py
aos/client.py
aos/design.py
aos/devices.py
aos/external_systems.py
aos/repeat.py
aos/resources.py
aos/telemetry.py
aos/utils.py
apstra_api_python-0.2.1.dist-info/LICENSE
apstra_api_python-0.2.1.dist-info/METADATA
apstra_api_python-0.2.1.dist-info/WHEEL
apstra_api_python-0.2.1.dist-info/top_level.txt
apstra_api_python-0.2.1.dist-info/RECORD
